{
  "id": "wj4no",
  "category": "armor/combined",
  "name": {
    "type": "translation",
    "key": "item.arm.albatros_heavy.name",
    "args": {},
    "lines": {
      "ru": "Бронескелет «Альбатрос-Штурмовик»",
      "en": "Albatross Heavy Assault Armored Exoskeleton",
      "es": "Exoesqueleto blindado Albatros de asalto pesado",
      "fr": "Exosquelette Blindé Albatros d\u0027Assaut"
    }
  },
  "color": "RANK_LEGEND",
  "status": {
    "state": "PERSONAL_ON_USE"
  },
  "infoBlocks": [
    {
      "type": "list",
      "title": {
        "type": "text",
        "text": ""
      },
      "elements": [
        {
          "type": "key-value",
          "key": {
            "type": "translation",
            "key": "core.tooltip.info.rank",
            "args": {},
            "lines": {
              "ru": "Ранг",
              "en": "Rank",
              "es": "Rango",
              "fr": "Rang"
            }
          },
          "value": {
            "type": "translation",
            "key": "core.rank.legend",
            "args": {},
            "lines": {
              "ru": "Легенда",
              "en": "Legend",
              "es": "Leyenda",
              "fr": "Légende"
            }
          }
        },
        {
          "type": "key-value",
          "key": {
            "type": "translation",
            "key": "core.tooltip.info.category",
            "args": {},
            "lines": {
              "ru": "Класс",
              "en": "Class",
              "es": "Clase",
              "fr": "Classe"
            }
          },
          "value": {
            "type": "translation",
            "key": "core.handbook.category.combined",
            "args": {},
            "lines": {
              "ru": "Комбинированные",
              "en": "Combo",
              "es": "Combo",
              "fr": "Combo"
            }
          }
        },
        {
          "type": "numeric",
          "name": {
            "type": "translation",
            "key": "core.tooltip.info.weight",
            "args": {},
            "lines": {
              "ru": "Вес",
              "en": "Weight",
              "es": "Peso",
              "fr": "Poids"
            }
          },
          "value": 37.0,
          "formatted": {
            "value": {
              "ru": "37 кг",
              "en": "37 kg",
              "es": "37 kg",
              "fr": "37 kg"
            },
            "nameColor": "838383",
            "valueColor": "838383"
          }
        },
        {
          "type": "numeric",
          "name": {
            "type": "translation",
            "key": "core.tooltip.info.durability",
            "args": {},
            "lines": {
              "ru": "Прочность",
              "en": "Durability",
              "es": "Durabilidad",
              "fr": "Durabilité"
            }
          },
          "value": 100.0,
          "formatted": {
            "value": {
              "ru": "100%",
              "en": "100%",
              "es": "100 %",
              "fr": "100%"
            },
            "nameColor": "838383",
            "valueColor": "838383"
          }
        },
        {
          "type": "numeric",
          "name": {
            "type": "translation",
            "key": "core.tooltip.info.max_durability",
            "args": {},
            "lines": {
              "ru": "Макс. прочность",
              "en": "Max. durability",
              "es": "Durabilidad máx.",
              "fr": "Durabilité Max."
            }
          },
          "value": 100.0,
          "formatted": {
            "value": {
              "ru": "100%",
              "en": "100%",
              "es": "100 %",
              "fr": "100%"
            },
            "nameColor": "838383",
            "valueColor": "838383"
          }
        }
      ]
    },
    {
      "type": "list",
      "title": {
        "type": "text",
        "text": ""
      },
      "elements": []
    },
    {
      "type": "list",
      "title": {
        "type": "text",
        "text": ""
      },
      "elements": []
    },
    {},
    {
      "type": "list",
      "title": {
        "type": "text",
        "text": ""
      },
      "elements": [
        {
          "type": "numeric",
          "name": {
            "type": "translation",
            "key": "stalker.artefact_properties.factor.max_weight_bonus",
            "args": {},
            "lines": {
              "ru": "Переносимый вес",
              "en": "Carry weight",
              "es": "Peso de carga",
              "fr": "Poids maximum supporté"
            }
          },
          "value": 30.0,
          "formatted": {
            "value": {
              "ru": "+30",
              "en": "+30",
              "es": "+30",
              "fr": "+30"
            },
            "nameColor": "53C353",
            "valueColor": "53C353"
          }
        },
        {
          "type": "numeric",
          "name": {
            "type": "translation",
            "key": "stalker.artefact_properties.factor.bleeding_accumulation",
            "args": {},
            "lines": {
              "ru": "Кровотечение",
              "en": "Bleeding",
              "es": "Hemorragia",
              "fr": "Saignement"
            }
          },
          "value": -1.0,
          "formatted": {
            "value": {
              "ru": "-1",
              "en": "-1",
              "es": "-1",
              "fr": "-1"
            },
            "nameColor": "53C353",
            "valueColor": "53C353"
          }
        }
      ]
    },
    {
      "type": "list",
      "title": {
        "type": "text",
        "text": ""
      },
      "elements": [
        {
          "type": "numeric",
          "name": {
            "type": "translation",
            "key": "stalker.artefact_properties.factor.bullet_dmg_factor",
            "args": {},
            "lines": {
              "ru": "Пулестойкость",
              "en": "Bullet resistance",
              "es": "Resistencia a las balas",
              "fr": "Résistance aux balles"
            }
          },
          "value": 279.35312,
          "formatted": {
            "value": {
              "ru": "279,35",
              "en": "279.35",
              "es": "279,35",
              "fr": "279,35"
            },
            "nameColor": "838383",
            "valueColor": "EEEEEE"
          }
        },
        {
          "type": "numeric",
          "name": {
            "type": "translation",
            "key": "stalker.artefact_properties.factor.tear_dmg_factor",
            "args": {},
            "lines": {
              "ru": "Защита от разрыва",
              "en": "Laceration protection",
              "es": "Protección contra laceración",
              "fr": "Protection contre les lacérations"
            }
          },
          "value": 159.0,
          "formatted": {
            "value": {
              "ru": "159",
              "en": "159",
              "es": "159",
              "fr": "159"
            },
            "nameColor": "838383",
            "valueColor": "EEEEEE"
          }
        },
        {
          "type": "numeric",
          "name": {
            "type": "translation",
            "key": "stalker.artefact_properties.factor.explosion_dmg_factor",
            "args": {},
            "lines": {
              "ru": "Защита от взрыва",
              "en": "Explosion protection",
              "es": "Protección contra explosiones",
              "fr": "Protection contre les explosions"
            }
          },
          "value": 140.0,
          "formatted": {
            "value": {
              "ru": "140",
              "en": "140",
              "es": "140",
              "fr": "140"
            },
            "nameColor": "838383",
            "valueColor": "EEEEEE"
          }
        },
        {
          "type": "numeric",
          "name": {
            "type": "translation",
            "key": "stalker.artefact_properties.factor.electra_dmg_factor",
            "args": {},
            "lines": {
              "ru": "Электрозащита",
              "en": "Resistance to electricity",
              "es": "Resistencia a la electricidad",
              "fr": "Résistance à l\u0027électricité"
            }
          },
          "value": 300.0,
          "formatted": {
            "value": {
              "ru": "300",
              "en": "300",
              "es": "300",
              "fr": "300"
            },
            "nameColor": "838383",
            "valueColor": "EEEEEE"
          }
        },
        {
          "type": "numeric",
          "name": {
            "type": "translation",
            "key": "stalker.artefact_properties.factor.burn_dmg_factor",
            "args": {},
            "lines": {
              "ru": "Защита от огня",
              "en": "Resistance to fire",
              "es": "Resistencia al fuego",
              "fr": "Résistance au feu"
            }
          },
          "value": 300.0,
          "formatted": {
            "value": {
              "ru": "300",
              "en": "300",
              "es": "300",
              "fr": "300"
            },
            "nameColor": "838383",
            "valueColor": "EEEEEE"
          }
        },
        {
          "type": "numeric",
          "name": {
            "type": "translation",
            "key": "stalker.artefact_properties.factor.chemical_burn_dmg_factor",
            "args": {},
            "lines": {
              "ru": "Химзащита",
              "en": "Resistance to chemicals",
              "es": "Resistencia a los productos químicos",
              "fr": "Résistance aux produits chimiques"
            }
          },
          "value": 300.0,
          "formatted": {
            "value": {
              "ru": "300",
              "en": "300",
              "es": "300",
              "fr": "300"
            },
            "nameColor": "838383",
            "valueColor": "EEEEEE"
          }
        },
        {
          "type": "numeric",
          "name": {
            "type": "translation",
            "key": "stalker.artefact_properties.factor.radiation_protection",
            "args": {},
            "lines": {
              "ru": "Защита от радиации",
              "en": "Radiation protection",
              "es": "Protección contra radiación",
              "fr": "Protection contre les radiations"
            }
          },
          "value": 300.0,
          "formatted": {
            "value": {
              "ru": "300",
              "en": "300",
              "es": "300",
              "fr": "300"
            },
            "nameColor": "838383",
            "valueColor": "EEEEEE"
          }
        },
        {
          "type": "numeric",
          "name": {
            "type": "translation",
            "key": "stalker.artefact_properties.factor.thermal_protection",
            "args": {},
            "lines": {
              "ru": "Защита от температуры",
              "en": "Thermal protection",
              "es": "Protección térmica",
              "fr": "Protection thermique"
            }
          },
          "value": 200.0,
          "formatted": {
            "value": {
              "ru": "200",
              "en": "200",
              "es": "200",
              "fr": "200"
            },
            "nameColor": "838383",
            "valueColor": "EEEEEE"
          }
        },
        {
          "type": "numeric",
          "name": {
            "type": "translation",
            "key": "stalker.artefact_properties.factor.biological_protection",
            "args": {},
            "lines": {
              "ru": "Защита от биозаражения",
              "en": "Bioinfection protection",
              "es": "Protección contra bioinfección",
              "fr": "Protection contre les bio infections"
            }
          },
          "value": 300.0,
          "formatted": {
            "value": {
              "ru": "300",
              "en": "300",
              "es": "300",
              "fr": "300"
            },
            "nameColor": "838383",
            "valueColor": "EEEEEE"
          }
        },
        {
          "type": "numeric",
          "name": {
            "type": "translation",
            "key": "stalker.artefact_properties.factor.psycho_protection",
            "args": {},
            "lines": {
              "ru": "Защита от пси-излучения",
              "en": "Psy-emission protection",
              "es": "Prot contra emisiones psy",
              "fr": "Protection contre les émissions psys"
            }
          },
          "value": 300.0,
          "formatted": {
            "value": {
              "ru": "300",
              "en": "300",
              "es": "300",
              "fr": "300"
            },
            "nameColor": "838383",
            "valueColor": "EEEEEE"
          }
        },
        {
          "type": "numeric",
          "name": {
            "type": "translation",
            "key": "stalker.artefact_properties.factor.bleeding_protection",
            "args": {},
            "lines": {
              "ru": "Защита от кровотечения",
              "en": "Bleeding Protection",
              "es": "Protección contra hemorragia",
              "fr": "Protection contre les saignements"
            }
          },
          "value": 40.0,
          "formatted": {
            "value": {
              "ru": "40%",
              "en": "40%",
              "es": "40 %",
              "fr": "40%"
            },
            "nameColor": "838383",
            "valueColor": "EEEEEE"
          }
        }
      ]
    },
    {
      "type": "list",
      "title": {
        "type": "translation",
        "key": "stalker.tooltip.armor_artefact.info.upgrade_stats",
        "args": {},
        "lines": {
          "ru": "Характеристики модификации",
          "en": "Modification properties",
          "es": "Propiedades de modificación",
          "fr": "Propriétés de modification"
        }
      },
      "elements": [
        {
          "type": "numeric",
          "name": {
            "type": "translation",
            "key": "stalker.artefact_properties.factor.bullet_dmg_factor",
            "args": {},
            "lines": {
              "ru": "Пулестойкость",
              "en": "Bullet resistance",
              "es": "Resistencia a las balas",
              "fr": "Résistance aux balles"
            }
          },
          "value": 40.353104,
          "formatted": {
            "value": {
              "ru": "40,35",
              "en": "40.35",
              "es": "40,35",
              "fr": "40,35"
            },
            "nameColor": "F1AA21",
            "valueColor": "F1AA21"
          }
        }
      ]
    },
    {
      "type": "text",
      "title": {
        "type": "translation",
        "key": "stalker.lore.armor_artefact.info.compatible_backpacks",
        "args": {},
        "lines": {
          "ru": "Совместимые рюкзаки",
          "en": "Compatible backpacks",
          "es": "Mochilas compatibles",
          "fr": "Sacs à dos compatibles"
        }
      },
      "text": {
        "type": "translation",
        "key": "general.armor.compatibility.backpacks.superheavy",
        "args": {},
        "lines": {
          "ru": "Любые",
          "en": "Any",
          "es": "Cualquiera",
          "fr": "Tous"
        }
      }
    },
    {
      "type": "text",
      "title": {
        "type": "translation",
        "key": "stalker.lore.armor_artefact.info.compatible_containers",
        "args": {},
        "lines": {
          "ru": "Совместимые контейнеры",
          "en": "Compatible containers",
          "es": "Contenedores compatibles",
          "fr": "Conteneurs compatibles"
        }
      },
      "text": {
        "type": "translation",
        "key": "general.armor.compatibility.containers.bulky",
        "args": {},
        "lines": {
          "ru": "Любые",
          "en": "Any",
          "es": "Cualquiera",
          "fr": "Tous"
        }
      }
    },
    {
      "type": "text",
      "title": {
        "type": "text",
        "text": ""
      },
      "text": {
        "type": "translation",
        "key": "item.arm.albatros_heavy.description",
        "args": {},
        "lines": {
          "ru": "Легендарная броня за авторством всем известной корпорации, поставляющей лучшую экзоброню для условий Зоны!\\n\\nНесмотря на то, что «Альбатрос-Штурмовик» использует общую для всех костюмов серии сервоприводную систему, при разработке этого костюма была проделана дополнительная модификация экзоскелета, что позволило не только улучшить защитные свойства «Штурмовика», но и сохранить мобильность.\\n\\nПередовые материалы и лучшее качество делают «Альбатрос-Штурмовик» одним из наиболее желанных костюмов среди сталкеров.",
          "en": "Legendary armor by the well-known corporation that supplies the best exoarmors for Zone conditions!\\n\\nAlthough the Albatross Heavy Assault Armored Exoskeleton uses the common servomotor system for all suits in the series, additional modifications to the exoskeleton were made during the development of this suit. This not only improved its protective properties but also maintained mobility.\\n\\nAdvanced materials and top quality make the Albatross Heavy Assault Armored Exoskeleton one of the most desired suits among stalkers.",
          "es": "Armadura legendaria de la famosa corporación que suministra la mejor exoarmadura para las condiciones de la Zona.\\n\\nA pesar de que Albatros de asalto pesado utiliza el sistema de servomotores común a todos los trajes de la serie, en el desarrollo de este traje se realizó una modificación adicional del exoesqueleto, lo que permitió no solo mejorar las propiedades protectoras de Asalto pesado, sino también mantener la movilidad.\\n\\nMateriales avanzados y la mejor calidad hacen de Albatros de asalto pesado uno de los trajes más codiciados entre los acechadores.",
          "fr": "Armure légendaire signée par la célèbre corporation fournissant l\u0027une des meilleures exo-armures pour la Zone.\\n\\nBien que l\u0027Albatros d\u0027Assaut partage le même système de servomoteurs que le reste de la gamme, des modifications supplémentaires de l\u0027exosquelette ont amélioré la protection de la version assaut tout en préservant la mobilité.\\n\\nDes matériaux de pointe et une qualité supérieure font de l\u0027Albatros d\u0027Assaut l\u0027une des combinaisons les plus convoitées chez les stalkers."
        }
      }
    }
  ]
}