{
  "id": "GLj9",
  "category": "medicine",
  "name": {
    "type": "translation",
    "key": "item.med.apt_p.name",
    "args": {},
    "lines": {
      "ru": "Аптечка проводника",
      "en": "Guide’s First-Aid Kit"
    }
  },
  "color": "DEFAULT",
  "status": {
    "state": "NONE"
  },
  "infoBlocks": [
    {
      "type": "list",
      "title": {
        "type": "text",
        "text": ""
      },
      "elements": [
        {
          "type": "key-value",
          "key": {
            "type": "translation",
            "key": "core.tooltip.info.category",
            "args": {},
            "lines": {
              "ru": "Класс",
              "en": "Class"
            }
          },
          "value": {
            "type": "translation",
            "key": "core.handbook.category.medicine",
            "args": {},
            "lines": {
              "ru": "Медикаменты",
              "en": "Medicine"
            }
          }
        },
        {
          "type": "numeric",
          "name": {
            "type": "translation",
            "key": "core.tooltip.info.weight",
            "args": {},
            "lines": {
              "ru": "Вес",
              "en": "Weight"
            }
          },
          "value": 0.2
        }
      ]
    },
    {
      "type": "list",
      "title": {
        "type": "text",
        "text": ""
      },
      "elements": []
    },
    {
      "type": "list",
      "title": {
        "type": "text",
        "text": ""
      },
      "elements": [
        {
          "type": "key-value",
          "key": {
            "type": "translation",
            "key": "stalker.tooltip.medicine.info.effect_type",
            "args": {},
            "lines": {
              "ru": "Назначение",
              "en": "Purpose"
            }
          },
          "value": {
            "type": "translation",
            "key": "item.effects.effect_type.healing",
            "args": {},
            "lines": {
              "ru": "Лечение",
              "en": "Healing"
            }
          }
        },
        {
          "type": "numeric",
          "name": {
            "type": "translation",
            "key": "stalker.tooltip.medicine.info.duration",
            "args": {},
            "lines": {
              "ru": "Время действия",
              "en": "Duration"
            }
          },
          "value": 10.0
        }
      ]
    },
    {
      "type": "list",
      "title": {
        "type": "text",
        "text": ""
      },
      "elements": [
        {
          "type": "numeric",
          "name": {
            "type": "translation",
            "key": "stalker.artefact_properties.factor.stamina_regeneration_bonus",
            "args": {},
            "lines": {
              "ru": "Восстановление выносливости",
              "en": "Stamina regeneration"
            }
          },
          "value": 15.0
        },
        {
          "type": "numeric",
          "name": {
            "type": "translation",
            "key": "stalker.artefact_properties.factor.artefakt_heal",
            "args": {},
            "lines": {
              "ru": "Периодическое лечение",
              "en": "Periodic healing"
            }
          },
          "value": 6.5
        },
        {
          "type": "numeric",
          "name": {
            "type": "translation",
            "key": "stalker.artefact_properties.factor.radiation_dmg_factor",
            "args": {},
            "lines": {
              "ru": "Сопротивление радиации",
              "en": "Radiation resistance"
            }
          },
          "value": 30.0
        },
        {
          "type": "numeric",
          "name": {
            "type": "translation",
            "key": "stalker.artefact_properties.factor.biological_dmg_factor",
            "args": {},
            "lines": {
              "ru": "Сопротивление биозаражению",
              "en": "Bioinfection resistance"
            }
          },
          "value": 30.0
        },
        {
          "type": "numeric",
          "name": {
            "type": "translation",
            "key": "stalker.artefact_properties.factor.radiation_accumulation",
            "args": {},
            "lines": {
              "ru": "Радиация",
              "en": "Radiation"
            }
          },
          "value": -5.0
        },
        {
          "type": "numeric",
          "name": {
            "type": "translation",
            "key": "stalker.artefact_properties.factor.biological_accumulation",
            "args": {},
            "lines": {
              "ru": "Биологическое заражение",
              "en": "Biological infection"
            }
          },
          "value": -5.0
        },
        {
          "type": "numeric",
          "name": {
            "type": "translation",
            "key": "stalker.artefact_properties.factor.bleeding_accumulation",
            "args": {},
            "lines": {
              "ru": "Кровотечение",
              "en": "Bleeding"
            }
          },
          "value": -1.5
        }
      ]
    },
    {
      "type": "text",
      "title": {
        "type": "text",
        "text": ""
      },
      "text": {
        "type": "translation",
        "key": "item.med.apt_p.description",
        "args": {},
        "lines": {
          "ru": "Аптечка с препаратами, собранными опытным сталкером. Содержит самые необходимые препараты в достаточной дозировке и подходит для любых ситуаций.",
          "en": "A first-aid kit with items assembled by an experienced stalker. Contains the most useful treatments in the right doses and is suitable for any situation."
        }
      }
    }
  ]
}