{
  "id": "3g05l",
  "category": "misc",
  "name": {
    "type": "translation",
    "key": "item.bag.armorpack_steel5.name",
    "args": {},
    "lines": {
      "ru": "Сумка стальных пластин V",
      "en": "Bag of Steel Plates V",
      "es": "Bolsa de placas de acero V"
    }
  },
  "color": "RANK_MASTER",
  "status": {
    "state": "NON_DROP"
  },
  "infoBlocks": [
    {
      "type": "list",
      "title": {
        "type": "text",
        "text": ""
      },
      "elements": [
        {
          "type": "key-value",
          "key": {
            "type": "translation",
            "key": "core.tooltip.info.rank",
            "args": {},
            "lines": {
              "ru": "Ранг",
              "en": "Rank",
              "es": "Rango"
            }
          },
          "value": {
            "type": "translation",
            "key": "core.rank.master",
            "args": {},
            "lines": {
              "ru": "Мастер",
              "en": "Master",
              "es": "Maestro"
            }
          }
        },
        {
          "type": "key-value",
          "key": {
            "type": "translation",
            "key": "core.tooltip.info.category",
            "args": {},
            "lines": {
              "ru": "Класс",
              "en": "Class",
              "es": "Clase"
            }
          },
          "value": {
            "type": "translation",
            "key": "core.handbook.category.misc",
            "args": {},
            "lines": {
              "ru": "Разное",
              "en": "Miscellaneous",
              "es": "Varios"
            }
          }
        },
        {
          "type": "numeric",
          "name": {
            "type": "translation",
            "key": "core.tooltip.info.weight",
            "args": {},
            "lines": {
              "ru": "Вес",
              "en": "Weight",
              "es": "Peso"
            }
          },
          "value": 15.0,
          "formatted": {
            "value": {
              "ru": "15 кг",
              "en": "15 kg",
              "es": "15 kg"
            },
            "nameColor": "838383",
            "valueColor": "838383"
          }
        },
        {
          "type": "numeric",
          "name": {
            "type": "translation",
            "key": "core.tooltip.info.durability",
            "args": {},
            "lines": {
              "ru": "Прочность",
              "en": "Durability",
              "es": "Durabilidad"
            }
          },
          "value": 100.0,
          "formatted": {
            "value": {
              "ru": "100%",
              "en": "100%",
              "es": "100 %"
            },
            "nameColor": "838383",
            "valueColor": "838383"
          }
        }
      ]
    },
    {
      "type": "list",
      "title": {
        "type": "text",
        "text": ""
      },
      "elements": []
    },
    {
      "type": "list",
      "title": {
        "type": "text",
        "text": ""
      },
      "elements": []
    },
    {},
    {
      "type": "list",
      "title": {
        "type": "text",
        "text": ""
      },
      "elements": [
        {
          "type": "key-value",
          "key": {
            "type": "translation",
            "key": "customitem.lore.command.info.usages_left",
            "args": {},
            "lines": {
              "ru": "Использований осталось",
              "en": "Uses remaining",
              "es": "Usos restantes"
            }
          },
          "value": {
            "type": "text",
            "text": "5/5"
          }
        }
      ]
    },
    {
      "type": "list",
      "title": {
        "type": "text",
        "text": ""
      },
      "elements": [
        {
          "type": "text",
          "text": {
            "type": "translation",
            "key": "item.info.command_item.content",
            "args": {},
            "lines": {
              "ru": "При использовании вы получите:",
              "en": "When you use it, you’ll get:",
              "es": "Al usar esto, obtendrás:"
            }
          }
        },
        {
          "type": "item",
          "name": {
            "type": "translation",
            "key": "item.plate.steel5.name",
            "args": {},
            "lines": {
              "ru": "Стальная пластина V",
              "en": "Steel Plate V",
              "es": "Placa de acero V"
            }
          }
        }
      ]
    }
  ]
}