{
  "id": "k3yv",
  "category": "artefact/other_arts",
  "name": {
    "type": "translation",
    "key": "item.art.murmur_hoop.name",
    "args": {},
    "lines": {
      "ru": "Обруч",
      "en": "Hoop",
      "es": "Aro",
      "fr": "Anneau",
      "ko": "고리"
    }
  },
  "color": "DEFAULT",
  "status": {
    "state": "NON_DROP"
  },
  "infoBlocks": [
    {
      "type": "list",
      "title": {
        "type": "text",
        "text": ""
      },
      "elements": [
        {
          "type": "key-value",
          "key": {
            "type": "translation",
            "key": "core.tooltip.info.category",
            "args": {},
            "lines": {
              "ru": "Класс",
              "en": "Class",
              "es": "Clase",
              "fr": "Classe",
              "ko": "등급"
            }
          },
          "value": {
            "type": "translation",
            "key": "core.handbook.category.other_arts",
            "args": {},
            "lines": {
              "ru": "Прочие",
              "en": "Other",
              "es": "Otros",
              "fr": "Autre",
              "ko": "기타"
            }
          }
        },
        {
          "type": "numeric",
          "name": {
            "type": "translation",
            "key": "core.tooltip.info.weight",
            "args": {},
            "lines": {
              "ru": "Вес",
              "en": "Weight",
              "es": "Peso",
              "fr": "Poids",
              "ko": "무게"
            }
          },
          "value": 0.3,
          "formatted": {
            "value": {
              "ru": "0,3 кг",
              "en": "0.3 kg",
              "es": "0,3 kg",
              "fr": "0,3 kg",
              "ko": "0.3 kg"
            },
            "nameColor": "838383",
            "valueColor": "838383"
          }
        }
      ]
    },
    {
      "type": "list",
      "title": {
        "type": "text",
        "text": ""
      },
      "elements": []
    },
    {
      "type": "list",
      "title": {
        "type": "text",
        "text": ""
      },
      "elements": []
    },
    {
      "type": "list",
      "title": {
        "type": "text",
        "text": ""
      },
      "elements": [
        {
          "type": "key-value",
          "key": {
            "type": "translation",
            "key": "core.tooltip.info.base_price",
            "args": {},
            "lines": {
              "ru": "Базовая цена продажи",
              "en": "Base selling price",
              "es": "Precio de venta base",
              "fr": "Prix de vente de base",
              "ko": "기본 판매 가격"
            }
          },
          "value": {
            "type": "translation",
            "key": "core.tooltip.info.rubles",
            "args": {
              "cost": "28640.0"
            },
            "lines": {
              "ru": "28 640 руб.",
              "en": "28,640 rubles",
              "es": "28.640 rublos",
              "fr": "28 640 roubles",
              "ko": "28,640 루블"
            }
          }
        }
      ]
    },
    {
      "type": "list",
      "title": {
        "type": "text",
        "text": ""
      },
      "elements": [
        {
          "type": "key-value",
          "key": {
            "type": "translation",
            "key": "core.quality.common",
            "args": {},
            "lines": {
              "ru": "Обычный",
              "en": "Common",
              "es": "Común",
              "fr": "Commun",
              "ko": "일반"
            }
          },
          "value": {
            "type": "translation",
            "key": "stalker.tooltip.artefact.not_probed",
            "args": {},
            "lines": {
              "ru": "Не исследовано",
              "en": "Not studied",
              "es": "No estudiado",
              "fr": "Non étudié",
              "ko": "연구되지 않음"
            }
          }
        }
      ]
    },
    {
      "type": "list",
      "title": {
        "type": "text",
        "text": ""
      },
      "elements": [
        {
          "type": "key-value",
          "key": {
            "type": "translation",
            "key": "stalker.tooltip.artefact.info.freshness",
            "args": {},
            "lines": {
              "ru": "Свежесть",
              "en": "Freshness",
              "es": "Frescura",
              "fr": "Fraîcheur",
              "ko": "품질"
            }
          },
          "value": {
            "type": "text",
            "text": "III"
          }
        },
        {
          "type": "numeric",
          "name": {
            "type": "translation",
            "key": "stalker.tooltip.artefact.info.durability",
            "args": {},
            "lines": {
              "ru": "Заряд",
              "en": "Charge",
              "es": "Carga",
              "fr": "Charge",
              "ko": "충전"
            }
          },
          "value": 100.0,
          "formatted": {
            "value": {
              "ru": "100%",
              "en": "100%",
              "es": "100 %",
              "fr": "100%",
              "ko": "100%"
            },
            "nameColor": "838383",
            "valueColor": "EEEEEE"
          }
        },
        {
          "type": "numeric",
          "name": {
            "type": "translation",
            "key": "stalker.tooltip.artefact.info.max_durability",
            "args": {},
            "lines": {
              "ru": "Макс. заряд",
              "en": "Max. charge",
              "es": "Carga máx.",
              "fr": "Charge maximale",
              "ko": "최대 충전량"
            }
          },
          "value": 100.0,
          "formatted": {
            "value": {
              "ru": "100%",
              "en": "100%",
              "es": "100 %",
              "fr": "100%",
              "ko": "100%"
            },
            "nameColor": "838383",
            "valueColor": "EEEEEE"
          }
        }
      ]
    },
    {
      "type": "list",
      "title": {
        "type": "text",
        "text": ""
      },
      "elements": [
        {
          "type": "range",
          "name": {
            "type": "translation",
            "key": "stalker.artefact_properties.factor.regeneration_bonus",
            "args": {},
            "lines": {
              "ru": "Регенерация здоровья",
              "en": "Health regeneration",
              "es": "Regeneración de salud",
              "fr": "Régénération de la santé",
              "ko": "체력 회복력"
            }
          },
          "min": 3.3728004,
          "max": 3.9680002,
          "formatted": {
            "value": {
              "ru": "[+3,37%; +3,97%]",
              "en": "[+3.37%; +3.97%]",
              "es": "[+3,37 %; +3,97 %]",
              "fr": "[+3,37%; +3,97%]",
              "ko": "[+3.37%; +3.97%]"
            },
            "nameColor": "53C353",
            "valueColor": "53C353"
          }
        },
        {
          "type": "range",
          "name": {
            "type": "translation",
            "key": "stalker.artefact_properties.factor.bullet_dmg_factor",
            "args": {},
            "lines": {
              "ru": "Пулестойкость",
              "en": "Bullet resistance",
              "es": "Resistencia a las balas",
              "fr": "Résistance aux balles",
              "ko": "총탄 보호율"
            }
          },
          "min": 9.5914,
          "max": 11.284,
          "formatted": {
            "value": {
              "ru": "[+9,59; +11,28]",
              "en": "[+9.59; +11.28]",
              "es": "[+9,59; +11,28]",
              "fr": "[+9,59; +11,28]",
              "ko": "[+9.59; +11.28]"
            },
            "nameColor": "53C353",
            "valueColor": "53C353"
          }
        },
        {
          "type": "range",
          "name": {
            "type": "translation",
            "key": "stalker.artefact_properties.factor.psycho_accumulation",
            "args": {},
            "lines": {
              "ru": "Пси-излучение",
              "en": "Psy-emissions",
              "es": "Emisiones psy",
              "fr": "Émissions psys",
              "ko": "정신파 방사물"
            }
          },
          "min": 2.125,
          "max": 2.5,
          "formatted": {
            "value": {
              "ru": "[+2,12; +2,5]",
              "en": "[+2.12; +2.5]",
              "es": "[+2,12; +2,5]",
              "fr": "[+2,12; +2,5]",
              "ko": "[+2.12; +2.5]"
            },
            "nameColor": "C15252",
            "valueColor": "C15252"
          }
        }
      ]
    },
    {
      "type": "text",
      "title": {
        "type": "text",
        "text": ""
      },
      "text": {
        "type": "translation",
        "key": "item.art.murmur_hoop.description",
        "args": {},
        "lines": {
          "ru": "Трофейный артефакт, полученный в боях с «Шепотом».\\nОбъект представляет собой спиралевидную твёрдую структуру неизвестного аномального образования, покрытую органическими клетками, которые можно отнести к царству грибов.\\nПри контакте с кожей отращивает тонкие белые нити, напоминающие мицелий и покрытые микроскопическими ворсинками, которые оплетают конечность или участок соприкосновения. Инвазивный характер воздействия не подтверждён.",
          "en": "A trophy artifact obtained from battles with Murmur.\\nThe object presents a spiral-shaped hard structure of unknown anomalous origin, covered with organic cells related to the fungus kingdom.\\nUpon skin contact, it grows thin white threads resembling mycelium, covered with microscopic villi, which envelop the limb or contact area. The invasive nature of the effect is not confirmed.",
          "es": "Artefacto trofeo obtenido en las batallas con Susurro.\\nEl objeto es una estructura sólida en forma de espiral de formación anormal desconocida, recubierta de células orgánicas que pueden atribuirse al reino de los hongos.\\nAl entrar en contacto con la piel, crecen finos hilos blancos parecidos al micelio y recubiertos de pelos microscópicos que trenzan el miembro o la zona de contacto. No se ha confirmado el carácter invasivo del efecto.",
          "fr": "Artefact trophée obtenu en affrontant le Murmure.\\nObjet constitué d\u0027une structure solide en spirale d\u0027origine anormale, recouverte de cellules organiques assimilables à des champignons.\\nAu contact de la peau, il déploie de fins filaments blancs semblables à du mycélium, couverts de micro-poils, qui s\u0027enroulent autour du membre ou de la zone de contact. Aucun caractère invasif confirmé.",
          "ko": "속삭임과의 전투에서 얻은 트로피 아티팩트. \\n균사류의 유기 세포로 덮여 있으며, 기원을 알 수 없는 나선형 모양의 단단한 이상 구조물이다. \\n피부에 닿으면 미세 융모로 덮여 있으며 균사체를 닮은 얇고 하얀 실을 뽑아내어 접촉 부위의 팔과 다리를 휘감는다. 침투성 여부는 아직 밝혀진 바 없다."
        }
      }
    }
  ]
}