{
  "id": "7l3n7",
  "category": "other",
  "name": {
    "type": "translation",
    "key": "item.style.wpn.vssm_spring25.name",
    "args": {},
    "lines": {
      "ru": "«Винт»",
      "en": "Vint",
      "es": "Perno",
      "fr": "Vis",
      "ko": "빈트"
    }
  },
  "color": "RANK_MASTER",
  "status": {
    "state": "PERSONAL_ON_USE"
  },
  "infoBlocks": [
    {
      "type": "list",
      "title": {
        "type": "text",
        "text": ""
      },
      "elements": [
        {
          "type": "key-value",
          "key": {
            "type": "translation",
            "key": "core.tooltip.info.rank",
            "args": {},
            "lines": {
              "ru": "Ранг",
              "en": "Rank",
              "es": "Rango",
              "fr": "Rang",
              "ko": "등급"
            }
          },
          "value": {
            "type": "translation",
            "key": "core.rank.master",
            "args": {},
            "lines": {
              "ru": "Мастер",
              "en": "Master",
              "es": "Maestro",
              "fr": "Maître",
              "ko": "마스터"
            }
          }
        },
        {
          "type": "key-value",
          "key": {
            "type": "translation",
            "key": "core.tooltip.info.category",
            "args": {},
            "lines": {
              "ru": "Класс",
              "en": "Class",
              "es": "Clase",
              "fr": "Classe",
              "ko": "등급"
            }
          },
          "value": {
            "type": "translation",
            "key": "core.handbook.category.weapon_style",
            "args": {},
            "lines": {
              "ru": "Облик оружия",
              "en": "Weapon Style",
              "es": "Estilo de armas",
              "fr": "Style d\u0027arme",
              "ko": "무기 외형"
            }
          }
        }
      ]
    },
    {
      "type": "list",
      "title": {
        "type": "text",
        "text": ""
      },
      "elements": []
    },
    {
      "type": "list",
      "title": {
        "type": "text",
        "text": ""
      },
      "elements": []
    },
    {
      "type": "text",
      "title": {
        "type": "text",
        "text": ""
      },
      "text": {
        "type": "translation",
        "key": "item.style.wpn.vssm_spring25.description",
        "args": {},
        "lines": {
          "ru": "Кастом от авторов Образца №47. Все тот же агрессивный вид и обещания, что это - лучший кастом, прямиком из мастерских первопроходцев Изнанки.",
          "en": "Custom from the authors of Model No. 47. The same aggressive look and promises that this is the best custom, straight from the workshops of The Inside Out pioneers.",
          "es": "La personalización de los autores de Modelo n.° 47. El mismo aspecto agresivo y promete que esta es la mejor personalización, directamente de los talleres de los pioneros del Reverso.",
          "fr": "Personnalisation des auteurs du Modèle No. 47. Le même look agressif et des promesses comme quoi ce serait la meilleur personnalisation, tout droit venu des ateliers des pionniers de l\u0027Envers.",
          "ko": "47번 모델 제작자들의 커스텀 버전. 공격적인 외모를 그대로 유지하면서 뒤집힌 세계의 선구자들이 직접 작업한 최고의 커스텀이라고 자부한다."
        }
      }
    },
    {}
  ]
}